10_practical_hdl_automation/02_alu_4_bit/ALU_4_bit.v
`timescale 1ns / 1ps

module ALU_4_bit(
    input  [3:0] a,b,
    input  [2:0] s,
    output reg [3:0] y,
    output reg carry,zero
);
    always @(*) begin
        carry = 0;
        case (s)
            3'b000 : {carry, y} = a + b;      // Add
            3'b001 : {carry, y} = a - b;      // Sub
            3'b010 : y = a & b;               // AND
            3'b011 : y = a | b;               // OR
            3'b100 : y = a ^ b;               // XOR
            3'b101 : y = ~a;                  // NOT(on a)
            3'b110 : y = a << b;              // Shift Left
            3'b111 : y = a >> b;              // Shift Right
            default: y = 4'b0000;             // Default 
        endcase

        zero = (y == 4'b0000) ? 1'b1 : 1'b0;
    end
endmodule

10_practical_hdl_automation/02_alu_4_bit/ALU_4_bit_tb.v
`timescale 1ns / 1ps
module ALU_4_bit_tb;

    reg [3:0] a,b;
    reg [2:0] s;
    wire [3:0] y;
    wire carry,zero;

    ALU_4_bit uut (.a(a), .b(b),.s(s),.y(y),.carry(carry),.zero(zero));

    initial begin
        // Initial
        a = 4'b1010; 
        b = 4'b0101;

        s = 3'b000; #10;
        $display("t=%0t, s=%b, y=%b, carry=%b, zero=%b", $time, s, y, carry, zero);

        s = 3'b001; #10;
        $display("t=%0t, s=%b, y=%b, carry=%b, zero=%b", $time, s, y, carry, zero);

        s = 3'b010; #10;
        $display("t=%0t, s=%b, y=%b, carry=%b, zero=%b", $time, s, y, carry, zero);

        s = 3'b011; #10;
        $display("t=%0t, s=%b, y=%b, carry=%b, zero=%b", $time, s, y, carry, zero);

        s = 3'b100; #10;
        $display("t=%0t, s=%b, y=%b, carry=%b, zero=%b", $time, s, y, carry, zero);

        s = 3'b101; #10;
        $display("t=%0t, s=%b, y=%b, carry=%b, zero=%b", $time, s, y, carry, zero);

        s = 3'b110; #10;
        $display("t=%0t, s=%b, y=%b, carry=%b, zero=%b", $time, s, y, carry, zero);

        s = 3'b111; #10;
        $display("t=%0t, s=%b, y=%b, carry=%b, zero=%b", $time, s, y, carry, zero);

        $finish;
    end

    initial begin
        $dumpfile("alu.vcd");
        $dumpvars(0, ALU_4_bit_tb);
    end

endmodule

10_practical_hdl_automation/02_alu_4_bit/alu.vcd
$date
	Sun Sep 27 11:51:08 2026
$end
$version
	Icarus Verilog
$end
$timescale
	1ps
$end
$scope module ALU_4_bit_tb $end
$var wire 1 ! zero $end
$var wire 4 " y [3:0] $end
$var wire 1 # carry $end
$var reg 4 $ a [3:0] $end
$var reg 4 % b [3:0] $end
$var reg 3 & s [2:0] $end
$scope module uut $end
$var wire 4 ' a [3:0] $end
$var wire 4 ( b [3:0] $end
$var wire 3 ) s [2:0] $end
$var reg 1 # carry $end
$var reg 4 * y [3:0] $end
$var reg 1 ! zero $end
$upscope $end
$upscope $end
$enddefinitions $end
$comment Show the parameter values. $end
$dumpall
$end
#0
$dumpvars
b1111 *
b0 )
b101 (
b1010 '
b0 &
b101 %
b1010 $
0#
b1111 "
0!
$end
#10000
b101 "
b101 *
b1 &
b1 )
#20000
1!
b0 "
b0 *
b10 &
b10 )
#30000
0!
b1111 "
b1111 *
b11 &
b11 )
#40000
b100 &
b100 )
#50000
b101 "
b101 *
b101 &
b101 )
#60000
1!
b0 "
b0 *
b110 &
b110 )
#70000
b111 &
b111 )
