10_practical_hdl_automation/01_d_flip_flop/D_flip_flop_behav.v
module D_flip_flop_behav(
    input d, clk,
    output reg q,
    output q_bar
);

    always @(posedge clk) begin
        q <= d;
    end
    assign q_bar = ~q;

endmodule

10_practical_hdl_automation/01_d_flip_flop/D_flip_flop_tb.v
module D_flip_flop_tb();
    reg d,clk;
    wire q,q_bar;

    // if using behavioural, uncomment the behav line and comment the gate line, or vice versa
    D_flip_flop_behav uut(.d(d),.clk(clk),.q(q),.q_bar(q_bar));
    // D_flip_flop_gate  uut(.d(d),.clk(clk),.q(q),.q_bar(q_bar));

    initial begin
        clk = 0;
        forever #5 clk = ~clk;
    end

    initial begin
       

        d = 0; #10;
        d = 1; #10;
        d = 0; #10;
        d = 1; #10;
        d = 1; #10;
        d = 0; #10;
        d = 0; #10;

        $finish;
    end

    initial begin
      $dumpfile("dff.vcd");
      $dumpvars(0, D_flip_flop_tb);
    end

endmodule

10_practical_hdl_automation/01_d_flip_flop/dff.vcd
$date
	Sun Sep 27 11:31:18 2026
$end
$version
	Icarus Verilog
$end
$timescale
	1s
$end
$scope module D_flip_flop_tb $end
$var wire 1 ! q_bar $end
$var wire 1 " q $end
$var reg 1 # clk $end
$var reg 1 $ d $end
$scope module uut $end
$var wire 1 # clk $end
$var wire 1 $ d $end
$var wire 1 ! q_bar $end
$var reg 1 " q $end
$upscope $end
$upscope $end
$enddefinitions $end
$comment Show the parameter values. $end
$dumpall
$end
#0
$dumpvars
0$
0#
x"
x!
$end
#5
1!
0"
1#
#10
0#
1$
#15
0!
1"
1#
#20
0#
0$
#25
1!
0"
1#
#30
0#
1$
#35
0!
1"
1#
#40
0#
#45
1#
#50
0#
0$
#55
1!
0"
1#
