10_practical_hdl_automation/03_uart/UART_Rx.v
`timescale 1ns / 1ps

module UART_Rx(
  input clk, reset, rx,
  output reg [7:0] data_out,
  output reg done
);
  reg [3:0] count;
  reg receiving;

  always @(posedge clk or posedge reset) begin
    if (reset) begin
      count <= 0;
      receiving <= 0;
      done <= 0;
    end
    else if (!receiving && rx == 0) begin
      receiving <= 1;    // start bit detected
      count <= 0;
      done <= 0;
    end
    else if (receiving) begin
      count <= count + 1;
      case(count)
        1: data_out[0] <= rx;
        2: data_out[1] <= rx;
        3: data_out[2] <= rx;
        4: data_out[3] <= rx;
        5: data_out[4] <= rx;
        6: data_out[5] <= rx;
        7: data_out[6] <= rx;
        8: data_out[7] <= rx;
        9: begin done <= 1; receiving <= 0; end // stop bit
      endcase
    end
  end
endmodule

10_practical_hdl_automation/03_uart/UART_Tx.v
`timescale 1ns / 1ps

module UART_Tx(
  input clk, reset, start,
  input [7:0] data,
  output reg tx
);
  reg [3:0] count;
  reg sending;

  always @(posedge clk or posedge reset) begin
    if (reset) begin
      tx <= 1;          // idle high
      count <= 0;
      sending <= 0;
    end
    else if (start && !sending) begin
      sending <= 1;
      count <= 0;
    end
    else if (sending) begin
      case(count)
        0: tx <= 0;             // start bit
        1: tx <= data[0];
        2: tx <= data[1];
        3: tx <= data[2];
        4: tx <= data[3];
        5: tx <= data[4];
        6: tx <= data[5];
        7: tx <= data[6];
        8: tx <= data[7];
        9: tx <= 1;             // stop bit
      endcase

      count <= count + 1;
      if (count == 9) sending <= 0;
    end
  end
endmodule

10_practical_hdl_automation/03_uart/UART_tb.v
`timescale 1ns / 1ps

module UART_tb();
  reg clk = 0, reset, start;
  reg [7:0] data;
  wire tx;
  wire [7:0] rx_data;
  wire done;

  UART_Tx TX(clk, reset, start, data, tx);
  UART_Rx RX(clk, reset, tx, rx_data, done);

  always #5 clk = ~clk; // clock

  initial begin
    
    reset = 1; start = 0; data = 8'h00;
    #10 reset = 0;

    #10 data = 8'hA5; start = 1; #10 start = 0; // send 0xA5
    wait(done);
    $display("Received: %h", rx_data);
    #20 $finish;
  end

  initial begin
    $dumpfile("uart.vcd");
    $dumpvars(0, UART_tb);
  end

endmodule

10_practical_hdl_automation/03_uart/uart.vcd
$date
	Sun Sep 27 11:47:45 2026
$end
$version
	Icarus Verilog
$end
$timescale
	1ps
$end
$scope module UART_tb $end
$var wire 1 ! tx $end
$var wire 8 " rx_data [7:0] $end
$var wire 1 # done $end
$var reg 1 $ clk $end
$var reg 8 % data [7:0] $end
$var reg 1 & reset $end
$var reg 1 ' start $end
$scope module RX $end
$var wire 1 $ clk $end
$var wire 1 & reset $end
$var wire 1 ! rx $end
$var reg 4 ( count [3:0] $end
$var reg 8 ) data_out [7:0] $end
$var reg 1 # done $end
$var reg 1 * receiving $end
$upscope $end
$scope module TX $end
$var wire 1 $ clk $end
$var wire 8 + data [7:0] $end
$var wire 1 & reset $end
$var wire 1 ' start $end
$var reg 4 , count [3:0] $end
$var reg 1 - sending $end
$var reg 1 ! tx $end
$upscope $end
$upscope $end
$enddefinitions $end
$comment Show the parameter values. $end
$dumpall
$end
#0
$dumpvars
0-
b0 ,
b0 +
0*
bx )
b0 (
0'
1&
b0 %
0$
0#
bx "
1!
$end
#5000
1$
#10000
0$
0&
#15000
1$
#20000
0$
1'
b10100101 %
b10100101 +
#25000
1-
1$
#30000
0$
0'
#35000
b1 ,
0!
1$
#40000
0$
#45000
1*
b10 ,
1!
1$
#50000
0$
#55000
b11 ,
0!
b1 (
1$
#60000
0$
#65000
bx0 "
bx0 )
b10 (
b100 ,
1!
1$
#70000
0$
#75000
b101 ,
0!
bx10 "
bx10 )
b11 (
1$
#80000
0$
#85000
bx010 "
bx010 )
b100 (
b110 ,
1$
#90000
0$
#95000
b111 ,
1!
bx0010 "
bx0010 )
b101 (
1$
#100000
0$
#105000
bx10010 "
bx10010 )
b110 (
b1000 ,
0!
1$
#110000
0$
#115000
b1001 ,
1!
bx010010 "
bx010010 )
b111 (
1$
#120000
0$
#125000
bx1010010 "
bx1010010 )
b1000 (
0-
b1010 ,
1$
#130000
0$
#135000
b11010010 "
b11010010 )
b1001 (
1$
#140000
0$
#145000
0*
1#
b1010 (
1$
